{
	"configurations" : 
	[
		{
			"directories" : 
			[
				{
					"build" : ".",
					"hasInstallRule" : true,
					"minimumCMakeVersion" : 
					{
						"string" : "3.5"
					},
					"projectIndex" : 0,
					"source" : ".",
					"targetIndexes" : 
					[
						0,
						1,
						2,
						3
					]
				}
			],
			"name" : "",
			"projects" : 
			[
				{
					"directoryIndexes" : 
					[
						0
					],
					"name" : "diffdrive_arduino",
					"targetIndexes" : 
					[
						0,
						1,
						2,
						3
					]
				}
			],
			"targets" : 
			[
				{
					"directoryIndex" : 0,
					"id" : "diffdrive_arduino::@6890427a1f51a3e7e1df",
					"jsonFile" : "target-diffdrive_arduino-c566cd765dad24e6eded.json",
					"name" : "diffdrive_arduino",
					"projectIndex" : 0
				},
				{
					"directoryIndex" : 0,
					"id" : "diffdrive_arduino_uninstall::@6890427a1f51a3e7e1df",
					"jsonFile" : "target-diffdrive_arduino_uninstall-3a5cd0d8501da69d2fe5.json",
					"name" : "diffdrive_arduino_uninstall",
					"projectIndex" : 0
				},
				{
					"directoryIndex" : 0,
					"id" : "fake_robot::@6890427a1f51a3e7e1df",
					"jsonFile" : "target-fake_robot-f00afbf448de10903059.json",
					"name" : "fake_robot",
					"projectIndex" : 0
				},
				{
					"directoryIndex" : 0,
					"id" : "uninstall::@6890427a1f51a3e7e1df",
					"jsonFile" : "target-uninstall-d4894132bb886789525d.json",
					"name" : "uninstall",
					"projectIndex" : 0
				}
			]
		}
	],
	"kind" : "codemodel",
	"paths" : 
	{
		"build" : "/home/abcs/robo_ws/build/diffdrive_arduino",
		"source" : "/home/abcs/robo_ws/src/diffdrive_arduino"
	},
	"version" : 
	{
		"major" : 2,
		"minor" : 0
	}
}
